{
    "Item": [
      {
        "description": "Aprender Angular",
        "date": "01/06/2021",
        "state": "undone"
      },
      {
        "description": "Aprender Bases de Datos",
        "date": "01/05/2021",
        "state": "undone"
      },
      {
        "description": "Entregar proyecto Angular",
        "date": "05/06/2021",
        "state": "undone"
      },
      {
        "description": "Aprender POO",
        "date": "05/06/2020",
        "state": "done"
      },
      {
        "description": "Finalizar carrera",
        "date": "05/06/2021",
        "state": "active"
      },
      {
        "description": "Empezar a leer Guerra y Paz",
        "date": "05/06/2021",
        "state": "undone"
      },
      {
        "description": "Escribir una reseña sobre el libro Rebecca",
        "date": "05/06/2021",
        "state": "done"
      },
      {
        "description": "To-Do List: impedir la creación de tareas vacías",
        "date": "05/06/2021",
        "state": "active"
      }
    ]
}
